gitgetpm/__init__.py
gitgetpm/cli.py
gitgetpm/version.py
gitgetpm/commands/__init__.py
gitgetpm/commands/_base.py
gitgetpm/commands/_updateprogress.py
gitgetpm/commands/doctor.py
gitgetpm/commands/edit.py
gitgetpm/commands/help.py
gitgetpm/commands/install.py
gitgetpm/commands/list.py
gitgetpm/commands/move.py
gitgetpm/commands/remove.py
gitgetpm/commands/setup.py
gitgetpm/commands/update.py
gitget_pm-2.3.0.dist-info/LICENSE.txt
gitget_pm-2.3.0.dist-info/METADATA
gitget_pm-2.3.0.dist-info/WHEEL
gitget_pm-2.3.0.dist-info/entry_points.txt
gitget_pm-2.3.0.dist-info/top_level.txt
gitget_pm-2.3.0.dist-info/RECORD
