Metadata-Version: 2.1
Name: gitget-pm
Version: 2.3.0
Summary: A package manager for git repositories.
Home-page: https://github.com/awesmubarak/gitget
Author: Awes Mubarak
Author-email: contact@awesmubarak.com
License: MIT
Keywords: git github package manager
Platform: UNKNOWN
Classifier: Development Status :: 5 - Production/Stable
Classifier: Intended Audience :: Developers
Classifier: Intended Audience :: End Users/Desktop
Classifier: Topic :: Software Development :: Version Control :: Git
Classifier: Operating System :: POSIX
Classifier: License :: OSI Approved :: MIT License
Classifier: Programming Language :: Python
Requires-Dist: docopt
Requires-Dist: loguru
Requires-Dist: gitpython
Requires-Dist: pyyaml
Requires-Dist: tabulate
